edwh_uptime_plugin/__about__.py
edwh_uptime_plugin/__init__.py
edwh_uptime_plugin/dumpers.py
edwh_uptime_plugin/helpers.py
edwh_uptime_plugin/tasks.py
edwh_uptime_plugin/uptimerobot.py
edwh_uptime_plugin-0.5.4.dist-info/METADATA
edwh_uptime_plugin-0.5.4.dist-info/WHEEL
edwh_uptime_plugin-0.5.4.dist-info/entry_points.txt
edwh_uptime_plugin-0.5.4.dist-info/RECORD
