Metadata-Version: 2.4
Name: edwh-uptime-plugin
Version: 0.5.4
Summary: UptimeRobot plugin for `edwh`
Project-URL: Documentation, https://github.com/educationwarehouse/edwh-uptime-plugin#readme
Project-URL: Issues, https://github.com/educationwarehouse/edwh-uptime-plugin/issues
Project-URL: Source, https://github.com/educationwarehouse/edwh-uptime-plugin
Author-email: Remco Boerma <remco.b@educationwarehouse.nl>, Robin van der Noord <robin.vdn@educationwarehouse.nl>
Keywords: edwh
Classifier: Development Status :: 4 - Beta
Classifier: Programming Language :: Python
Classifier: Programming Language :: Python :: 3.10
Classifier: Programming Language :: Python :: 3.11
Classifier: Programming Language :: Python :: 3.12
Classifier: Programming Language :: Python :: Implementation :: CPython
Classifier: Programming Language :: Python :: Implementation :: PyPy
Requires-Python: >=3.10
Requires-Dist: edwh>=0.38.0
Requires-Dist: termcolor
Requires-Dist: tomli-w
Requires-Dist: typing-extensions
Requires-Dist: yayarl
Provides-Extra: dev
Requires-Dist: black; extra == 'dev'
Requires-Dist: hatch; extra == 'dev'
Requires-Dist: isort; extra == 'dev'
Requires-Dist: pytest; extra == 'dev'
Requires-Dist: pytest-cov; extra == 'dev'
